molecule_glesys/__init__.py
molecule_glesys/driver.py
molecule_glesys-0.7.dist-info/licenses/LICENSE
molecule_glesys-0.7.dist-info/METADATA
molecule_glesys-0.7.dist-info/WHEEL
molecule_glesys-0.7.dist-info/entry_points.txt
molecule_glesys-0.7.dist-info/top_level.txt
molecule_glesys-0.7.dist-info/RECORD
