Metadata-Version: 2.4
Name: molecule-glesys
Version: 0.7
Summary: Molecule Glesys Plugin :: run molecule tests in Glesys Cloud
Home-page: https://github.com/glesys/molecule-driver
Author: Magnus Johansson
Author-email: magnus@glesys.se
Classifier: Programming Language :: Python :: 3
Classifier: Programming Language :: Python :: 3.10
Classifier: Programming Language :: Python :: 3.11
Classifier: Programming Language :: Python :: 3.12
Classifier: Operating System :: OS Independent
Requires-Python: >=3.10
License-File: LICENSE
Requires-Dist: PyYAML
Dynamic: author
Dynamic: author-email
Dynamic: classifier
Dynamic: description
Dynamic: description-content-type
Dynamic: home-page
Dynamic: license-file
Dynamic: requires-dist
Dynamic: requires-python
Dynamic: summary
